AEFM/__init__.py
AEFM/__main__.py
AEFM/cli/__init__.py
AEFM/cli/commands.py
AEFM/cli/config_template.py
AEFM/cli/messages.py
AEFM/cli/utils.py
AEFM/configs/__init__.py
AEFM/data_collector/__init__.py
AEFM/data_collector/base.py
AEFM/data_collector/interfaces.py
AEFM/data_collector/jaeger_trace_collector.py
AEFM/data_collector/models.py
AEFM/data_collector/prom_hardware_collector.py
AEFM/data_collector/wrk_throughput_collector.py
AEFM/deployer/__init__.py
AEFM/deployer/base.py
AEFM/deployer/init_media_microsvc_1.py
AEFM/deployer/init_media_microsvc_2.py
AEFM/deployer/init_social_network.py
AEFM/deployer/intrefaces.py
AEFM/deployer/datasets/social-graph/ego-twitter/ego-twitter-original.txt
AEFM/deployer/datasets/social-graph/ego-twitter/ego-twitter.edges
AEFM/deployer/datasets/social-graph/ego-twitter/ego-twitter.nodes
AEFM/deployer/datasets/social-graph/ego-twitter/readme.md
AEFM/deployer/datasets/social-graph/soc-twitter-follows-mun/readme.html
AEFM/deployer/datasets/social-graph/soc-twitter-follows-mun/soc-twitter-follows-mun.edges
AEFM/deployer/datasets/social-graph/soc-twitter-follows-mun/soc-twitter-follows-mun.nodes
AEFM/deployer/datasets/social-graph/socfb-Reed98/readme.html
AEFM/deployer/datasets/social-graph/socfb-Reed98/socfb-Reed98.edges
AEFM/deployer/datasets/social-graph/socfb-Reed98/socfb-Reed98.nodes
AEFM/deployer/datasets/tmdb/casts-tiny.json
AEFM/deployer/datasets/tmdb/casts.json
AEFM/deployer/datasets/tmdb/get_casts.py
AEFM/deployer/datasets/tmdb/get_movies.py
AEFM/deployer/datasets/tmdb/movies-tiny.json
AEFM/deployer/datasets/tmdb/movies.json
AEFM/inf_generator/__init__.py
AEFM/inf_generator/base.py
AEFM/inf_generator/interfaces.py
AEFM/inf_generator/templates/interference.yaml
AEFM/inf_generator/templates/net-inf.yaml
AEFM/manager/__init__.py
AEFM/manager/base.py
AEFM/manager/events.py
AEFM/manager/interfaces.py
AEFM/models/__init__.py
AEFM/models/node.py
AEFM/models/pod_spec.py
AEFM/models/test_case.py
AEFM/models/test_cases.py
AEFM-0.2.0.dist-info/METADATA
AEFM-0.2.0.dist-info/WHEEL
AEFM-0.2.0.dist-info/top_level.txt
AEFM-0.2.0.dist-info/RECORD
