Metadata-Version: 2.1
Name: AEFM
Version: 0.2.0
Summary: An automatic experiment framework for microservice.
Author-email: Nick Lin <nicklin9907@gmail.com>
License: GNU GENERAL PUBLIC LICENSE
Requires-Python: >=3.11
Requires-Dist: termcolor >=2.3.0
Requires-Dist: aiohttp >=3.8.5
Requires-Dist: ipdb >=0.13.13
Requires-Dist: PyYAML >=6.0
Requires-Dist: kubernetes >=27.2.0
Requires-Dist: pandas >=1.1.5
Requires-Dist: click >=8.1.7
